skfurigana/__init__.py
skfurigana/chat_assistant_provider.py
skfurigana/furigana.py
skfurigana-0.1.6.dist-info/licenses/LICENSE
skfurigana-0.1.6.dist-info/METADATA
skfurigana-0.1.6.dist-info/WHEEL
skfurigana-0.1.6.dist-info/top_level.txt
skfurigana-0.1.6.dist-info/RECORD
