Metadata-Version: 2.4
Name: skfurigana
Version: 0.1.6
Summary: 日本語テキストにふりがなを付与するツール
Author: sugarkwork
License: MIT
Project-URL: Homepage, https://github.com/sugarkwork/furigana
Classifier: Programming Language :: Python :: 3
Classifier: Programming Language :: Python :: 3.8
Classifier: License :: OSI Approved :: MIT License
Classifier: Operating System :: OS Independent
Classifier: Development Status :: 3 - Alpha
Classifier: Intended Audience :: Developers
Classifier: Natural Language :: Japanese
Requires-Python: >=3.8
License-File: LICENSE
Requires-Dist: fugashi[unidic]
Requires-Dist: unidic
Requires-Dist: skpmem
Requires-Dist: json_repair
Requires-Dist: chat_assistant
Dynamic: license-file
